shadowfinder/__init__.py
shadowfinder/__main__.py
shadowfinder/cli.py
shadowfinder/shadowfinder.py
shadowfinder-0.6.0.dist-info/LICENSE
shadowfinder-0.6.0.dist-info/METADATA
shadowfinder-0.6.0.dist-info/WHEEL
shadowfinder-0.6.0.dist-info/entry_points.txt
shadowfinder-0.6.0.dist-info/RECORD
